vicommithooks/__init__.py
vicommithooks/__main__.py
vicommithooks/attributes.py
vicommithooks/version.py
vicommithooks-0.1.3.dist-info/entry_points.txt
vicommithooks-0.1.3.dist-info/LICENSE
vicommithooks-0.1.3.dist-info/WHEEL
vicommithooks-0.1.3.dist-info/METADATA
vicommithooks-0.1.3.dist-info/RECORD
