Metadata-Version: 2.1
Name: vicommithooks
Version: 0.1.3
Summary: Useful VI assertions that can be used to prevent bad project commits
License: MIT
Author: strainmike
Requires-Python: >=3.7.0,<4.0.0
Classifier: License :: OSI Approved :: MIT License
Classifier: Programming Language :: Python :: 3
Classifier: Programming Language :: Python :: 3.10
Classifier: Programming Language :: Python :: 3.7
Classifier: Programming Language :: Python :: 3.8
Classifier: Programming Language :: Python :: 3.9
Requires-Dist: pylabview-helpers (>=0.1.2,<0.2.0)
